Metadata-Version: 1.0
Name: ossuapi
Version: 0.1
Summary: just a small wrapper for osuapi
Home-page: UNKNOWN
Author: Kisei
Author-email: UNKNOWN
License: MIT
Platform: UNKNOWN
